enablebanking_sdk/__init__.py
enablebanking_sdk/constants/__init__.py
enablebanking_sdk/constants/account_balance_type.py
enablebanking_sdk/constants/address_type.py
enablebanking_sdk/constants/authentication_approach.py
enablebanking_sdk/constants/psu_type.py
enablebanking_sdk/constants/scheme_name.py
enablebanking_sdk/constants/transaction_fetch_strategy.py
enablebanking_sdk/exceptions.py
enablebanking_sdk/models/__init__.py
enablebanking_sdk/models/aspsp.py
enablebanking_sdk/models/balances.py
enablebanking_sdk/models/eb_party.py
enablebanking_sdk/samples/__init__.py
enablebanking_sdk/samples/authorize_session.py
enablebanking_sdk/service/__init__.py
enablebanking_sdk/service/integration.py
enablebanking_sdk/service/service.py
enablebanking_sdk-0.1.5.dist-info/METADATA
enablebanking_sdk-0.1.5.dist-info/WHEEL
enablebanking_sdk-0.1.5.dist-info/licenses/LICENSE
enablebanking_sdk-0.1.5.dist-info/RECORD
