Metadata-Version: 2.4
Name: enablebanking_sdk
Version: 0.1.5
Summary: 
License: MIT
License-File: LICENSE
Author: NOCFO
Author-email: team@nocfo.io
Requires-Python: >=3.11,<4.0
Classifier: License :: OSI Approved :: MIT License
Classifier: Programming Language :: Python :: 3
Classifier: Programming Language :: Python :: 3.11
Classifier: Programming Language :: Python :: 3.12
Classifier: Programming Language :: Python :: 3.13
Classifier: Programming Language :: Python :: 3.14
Requires-Dist: cryptography (>=44.0.1,<45.0.0)
Requires-Dist: pydantic (>=2.9.2,<3.0.0)
Requires-Dist: pyjwt (>=2.9.0,<3.0.0)
Requires-Dist: requests (>=2.32.3,<3.0.0)
Project-URL: Bug Tracker, https://github.com/nocfo/enablebanking_sdk/issues
Project-URL: Homepage, https://github.com/nocfo/enablebanking_sdk
